topsis/101903706.py
topsis/__init__.py
topsis/test.py
topsis/topsis.py
Topsis_Rohit_101903706-1.0.1.dist-info/METADATA
Topsis_Rohit_101903706-1.0.1.dist-info/WHEEL
Topsis_Rohit_101903706-1.0.1.dist-info/entry_points.txt
Topsis_Rohit_101903706-1.0.1.dist-info/top_level.txt
Topsis_Rohit_101903706-1.0.1.dist-info/RECORD
